deltakit_circuit/__init__.py
deltakit_circuit/_basic_maps.py
deltakit_circuit/_basic_types.py
deltakit_circuit/_circuit.py
deltakit_circuit/_detector_manipulation.py
deltakit_circuit/_gate_layer.py
deltakit_circuit/_noise_factory.py
deltakit_circuit/_noise_layer.py
deltakit_circuit/_parse_stim.py
deltakit_circuit/_qubit_identifiers.py
deltakit_circuit/_qubit_mapping.py
deltakit_circuit/_stim_identifiers.py
deltakit_circuit/_stim_version_compatibility.py
deltakit_circuit/_version.pyi
deltakit_circuit/py.typed
deltakit_circuit/_annotations/_detector.py
deltakit_circuit/_annotations/_observable.py
deltakit_circuit/_annotations/_shift_coordinates.py
deltakit_circuit/gates/__init__.py
deltakit_circuit/gates/_abstract_gates.py
deltakit_circuit/gates/_measurement_gates.py
deltakit_circuit/gates/_one_qubit_gates.py
deltakit_circuit/gates/_reset_gates.py
deltakit_circuit/gates/_two_qubit_gates.py
deltakit_circuit/noise_channels/__init__.py
deltakit_circuit/noise_channels/_abstract_noise_channels.py
deltakit_circuit/noise_channels/_correlated_noise.py
deltakit_circuit/noise_channels/_depolarising_noise.py
deltakit_circuit/noise_channels/_leakage_noise.py
deltakit_circuit/noise_channels/_pauli_noise.py
deltakit_circuit-0.6.2.dist-info/licenses/LICENSE
deltakit_circuit-0.6.2.dist-info/METADATA
deltakit_circuit-0.6.2.dist-info/WHEEL
deltakit_circuit-0.6.2.dist-info/top_level.txt
deltakit_circuit-0.6.2.dist-info/RECORD
